dora_kokoro_tts/__init__.py
dora_kokoro_tts/__main__.py
dora_kokoro_tts/main.py
dora_kokoro_tts-0.4.1.dist-info/METADATA
dora_kokoro_tts-0.4.1.dist-info/WHEEL
dora_kokoro_tts-0.4.1.dist-info/entry_points.txt
dora_kokoro_tts-0.4.1.dist-info/top_level.txt
dora_kokoro_tts-0.4.1.dist-info/RECORD
