Metadata-Version: 2.4
Name: dora-kokoro-tts
Version: 0.4.1
Summary: dora-kokoro-tts
Author-email: Your Name <email@email.com>
License: MIT
Requires-Python: >=3.10
Requires-Dist: dora-rs>=0.3.9
Requires-Dist: kokoro>=0.2.2
Requires-Dist: soundfile>=0.13.1
Requires-Dist: misaki[zh]
Requires-Dist: en-core-web-sm
